Metadata-Version: 1.1
Name: django-saml2-auth-metadata-inline
Version: 0.0.8
Summary: Inline metadata plugin for django-saml2-auth
Home-page: https://github.com/ambsw/django-saml2-auth-metadata-inline
Author: Clayton Daley
Author-email: technology+saml2_metadata_plugin@gmail.com
License: Apache 2.0
Keywords: Django SAML2 Plugin for Inline Metadata
Platform: UNKNOWN
Classifier: Development Status :: 3 - Alpha
Classifier: Intended Audience :: Developers
Classifier: Topic :: Software Development :: Libraries :: Python Modules
Classifier: License :: OSI Approved :: Apache Software License
Classifier: Framework :: Django :: 1.5
Classifier: Framework :: Django :: 1.6
Classifier: Framework :: Django :: 1.7
Classifier: Framework :: Django :: 1.8
Classifier: Framework :: Django :: 1.9
Classifier: Framework :: Django :: 1.10
Classifier: Programming Language :: Python :: 2
Classifier: Programming Language :: Python :: 2.6
Classifier: Programming Language :: Python :: 2.7
Classifier: Programming Language :: Python :: 3
Classifier: Programming Language :: Python :: 3.3
Classifier: Programming Language :: Python :: 3.4
Classifier: Programming Language :: Python :: 3.5
Classifier: Programming Language :: Python :: 3.6
